Metadata-Version: 2.1
Name: rimvydas-zilinskas-lotr-api
Version: 0.1.0
Summary: Lord Of The Rings API
Home-page: https://github.com/rimvydaszilinskas/rimvydas-zilinskas-lotr-api
Author: Rimvydas Zilinskas
Author-email: rimvydas@meilirobots.com
License: UNKNOWN
Platform: UNKNOWN
